{
    "scope_1": {
        "mean_rmse": 112325.65123663543,
        "std_rmse": 16071.341687558717,
        "mean_mse": 12875339949.372517,
        "std_mse": 3796439145.4290466,
        "mean_mae": 51272.13258063407,
        "std_mae": 5777.519586096286,
        "mean_log_rmse": 2.0166782375982524,
        "std_log_rmse": 0.13909123487871103,
        "mean_log_mse": 4.086337485622478,
        "std_log_mse": 0.565654898817068,
        "mean_log_mae": 1.5949096631255426,
        "std_log_mae": 0.1274025515863234,
        "top_5_errors": {
            "420": {
                "actual": 637605.0,
                "predicted": 58401.158158157836,
                "abs_error": 579203.8418418422
            },
            "424": {
                "actual": 631252.0,
                "predicted": 62279.22384545366,
                "abs_error": 568972.7761545463
            },
            "150": {
                "actual": 568478.0,
                "predicted": 5540.533146363644,
                "abs_error": 562937.4668536363
            },
            "416": {
                "actual": 559769.0,
                "predicted": 1817.2439459363572,
                "abs_error": 557951.7560540637
            },
            "396": {
                "actual": 577624.0,
                "predicted": 23953.40042158745,
                "abs_error": 553670.5995784126
            }
        }
    },
    "scope_2": {
        "mean_rmse": 157404.553463799,
        "std_rmse": 88149.02101803782,
        "mean_mse": 32546443357.576427,
        "std_mse": 30487258935.630375,
        "mean_mae": 52482.24023667971,
        "std_mae": 19995.560760969445,
        "mean_log_rmse": 2.443273065146357,
        "std_log_rmse": 0.16856708767499226,
        "mean_log_mse": 5.997998133916902,
        "std_log_mse": 0.8307961952829731,
        "mean_log_mae": 1.7572288782361425,
        "std_log_mae": 0.05019663048100289,
        "top_5_errors": {
            "428": {
                "actual": 2061608.0,
                "predicted": 5309.078161865988,
                "abs_error": 2056298.921838134
            },
            "427": {
                "actual": 1597469.0,
                "predicted": 15196.207986834403,
                "abs_error": 1582272.7920131655
            },
            "426": {
                "actual": 1503357.0,
                "predicted": 28239.284604778622,
                "abs_error": 1475117.7153952215
            },
            "425": {
                "actual": 1105788.0,
                "predicted": 57691.52886220294,
                "abs_error": 1048096.4711377971
            },
            "424": {
                "actual": 862769.0,
                "predicted": 62738.37695362447,
                "abs_error": 800030.6230463756
            }
        }
    }
}